python_cassandra_cli/__init__.py
python_cassandra_cli/__main__.py
python_cassandra_cli/aws_utils.py
python_cassandra_cli/constant.py
python_cassandra_cli/constants.py
python_cassandra_cli/copy_snapshot_folder.py
python_cassandra_cli/main.py
python_cassandra_cli/restore_backup_keyspace.py
python_cassandra_cli/restore_snapshot_keyspace.py
python_cassandra_cli/restore_snapshot_table.py
python_cassandra_cli/store_backup_keyspace.py
python_cassandra_cli/store_snapshot_keyspace.py
python_cassandra_cli/store_snapshot_table.py
python_cassandra_cli-1.4.0.dist-info/LICENCE
python_cassandra_cli-1.4.0.dist-info/METADATA
python_cassandra_cli-1.4.0.dist-info/WHEEL
python_cassandra_cli-1.4.0.dist-info/entry_points.txt
python_cassandra_cli-1.4.0.dist-info/top_level.txt
python_cassandra_cli-1.4.0.dist-info/RECORD
