Metadata-Version: 2.1
Name: python-cassandra-cli
Version: 1.4.0
Summary: Python CLI for cassandra snapshots. CLI allows to store and restore snapshot and uses AWS S3 bucket as storage.
Home-page: 
Author: Andrii Derevianko
Author-email: sof2025@gmail.com
Keywords: snapshot python package cassandra backup migration
Classifier: Programming Language :: Python :: 3.6
Classifier: License :: OSI Approved :: MIT License
Classifier: Operating System :: OS Independent
Requires-Python: >=3.6
License-File: LICENCE
Requires-Dist: boto3 (==1.19.7)
Requires-Dist: botocore (==1.22.7)
Requires-Dist: click (==8.0.3)
Requires-Dist: six (==1.16.0)
Requires-Dist: python-dotenv (==0.21.0)
Requires-Dist: cassandra-driver (==3.25.0)
